{
  "Semantics": {
    "surface": {
      "page": {
        "light": {
          "$type": "color",
          "$value": "{Primitives.color/grey/50}",
          "$description": "Main page background"
        },
        "dark": {
          "$type": "color",
          "$value": "{Primitives.color/grey/950}",
          "$description": "Main page background"
        }
      },
      "subtle": {
        "light": {
          "$type": "color",
          "$value": "{Primitives.color/grey/100}",
          "$description": "Sidebars, zebra rows"
        },
        "dark": {
          "$type": "color",
          "$value": "{Primitives.color/grey/900}",
          "$description": "Sidebars, zebra rows"
        }
      },
      "card": {
        "light": {
          "$type": "color",
          "$value": "{Primitives.color/grey/50}",
          "$description": "Article cards, tiles"
        },
        "dark": {
          "$type": "color",
          "$value": "{Primitives.color/grey/800}",
          "$description": "Article cards, tiles"
        }
      },
      "overlay": {
        "light": {
          "$type": "color",
          "$value": "{Primitives.color/grey/50}",
          "$description": "Modals, drawers"
        },
        "dark": {
          "$type": "color",
          "$value": "{Primitives.color/grey/900}",
          "$description": "Modals, drawers"
        }
      },
      "inverse": {
        "light": {
          "$type": "color",
          "$value": "{Primitives.color/grey/900}",
          "$description": "Inverse surface"
        },
        "dark": {
          "$type": "color",
          "$value": "{Primitives.color/grey/50}",
          "$description": "Inverse surface"
        }
      },
      "brand": {
        "light": {
          "$type": "color",
          "$value": "{Primitives.color/red/600}",
          "$description": "Brand red surface"
        },
        "dark": {
          "$type": "color",
          "$value": "{Primitives.color/red/600}",
          "$description": "Brand red surface"
        }
      },
      "brand-subtle": {
        "light": {
          "$type": "color",
          "$value": "{Primitives.color/red/50}",
          "$description": "Tinted brand surface"
        },
        "dark": {
          "$type": "color",
          "$value": "{Primitives.color/red/950}",
          "$description": "Tinted brand surface"
        }
      },
      "breaking": {
        "light": {
          "$type": "color",
          "$value": "{Primitives.color/red/600}",
          "$description": "Breaking news banner"
        },
        "dark": {
          "$type": "color",
          "$value": "{Primitives.color/red/500}",
          "$description": "Breaking news banner"
        }
      },
      "scrim": {
        "light": {
          "$type": "color",
          "$value": "{Primitives.color/grey/900}",
          "$description": "Modal backdrop"
        },
        "dark": {
          "$type": "color",
          "$value": "{Primitives.color/grey/900}",
          "$description": "Modal backdrop"
        }
      }
    },
    "text": {
      "default": {
        "light": {
          "$type": "color",
          "$value": "{Primitives.color/grey/900}",
          "$description": "Primary body text"
        },
        "dark": {
          "$type": "color",
          "$value": "{Primitives.color/grey/50}",
          "$description": "Primary body text"
        }
      },
      "muted": {
        "light": {
          "$type": "color",
          "$value": "{Primitives.color/grey/600}",
          "$description": "Bylines, timestamps, metadata"
        },
        "dark": {
          "$type": "color",
          "$value": "{Primitives.color/grey/400}",
          "$description": "Bylines, timestamps, metadata"
        }
      },
      "subtle": {
        "light": {
          "$type": "color",
          "$value": "{Primitives.color/grey/400}",
          "$description": "Placeholders, disabled"
        },
        "dark": {
          "$type": "color",
          "$value": "{Primitives.color/grey/600}",
          "$description": "Placeholders, disabled"
        }
      },
      "inverted": {
        "light": {
          "$type": "color",
          "$value": "{Primitives.color/grey/50}",
          "$description": "Text on dark surfaces"
        },
        "dark": {
          "$type": "color",
          "$value": "{Primitives.color/grey/900}",
          "$description": "Text on dark surfaces"
        }
      },
      "heading": {
        "light": {
          "$type": "color",
          "$value": "{Primitives.color/grey/950}",
          "$description": "Headlines, section titles"
        },
        "dark": {
          "$type": "color",
          "$value": "{Primitives.color/grey/50}",
          "$description": "Headlines, section titles"
        }
      },
      "link": {
        "light": {
          "$type": "color",
          "$value": "{Primitives.color/blue/600}",
          "$description": "Hyperlinks"
        },
        "dark": {
          "$type": "color",
          "$value": "{Primitives.color/blue/300}",
          "$description": "Hyperlinks"
        }
      },
      "link-hover": {
        "light": {
          "$type": "color",
          "$value": "{Primitives.color/blue/700}",
          "$description": "Hovered links"
        },
        "dark": {
          "$type": "color",
          "$value": "{Primitives.color/blue/200}",
          "$description": "Hovered links"
        }
      },
      "link-visited": {
        "light": {
          "$type": "color",
          "$value": "{Primitives.color/blue/800}",
          "$description": "Visited links"
        },
        "dark": {
          "$type": "color",
          "$value": "{Primitives.color/blue/400}",
          "$description": "Visited links"
        }
      },
      "breaking": {
        "light": {
          "$type": "color",
          "$value": "{Primitives.color/red/600}",
          "$description": "Breaking news label"
        },
        "dark": {
          "$type": "color",
          "$value": "{Primitives.color/red/400}",
          "$description": "Breaking news label"
        }
      },
      "on-brand": {
        "light": {
          "$type": "color",
          "$value": "{Primitives.color/grey/50}",
          "$description": "Text on brand surfaces"
        },
        "dark": {
          "$type": "color",
          "$value": "{Primitives.color/grey/50}",
          "$description": "Text on brand surfaces"
        }
      },
      "on-inverse": {
        "light": {
          "$type": "color",
          "$value": "{Primitives.color/grey/50}",
          "$description": "Text on inverse surfaces"
        },
        "dark": {
          "$type": "color",
          "$value": "{Primitives.color/grey/900}",
          "$description": "Text on inverse surfaces"
        }
      }
    },
    "border": {
      "default": {
        "light": {
          "$type": "color",
          "$value": "{Primitives.color/grey/200}",
          "$description": "Default borders, dividers"
        },
        "dark": {
          "$type": "color",
          "$value": "{Primitives.color/grey/700}",
          "$description": "Default borders, dividers"
        }
      },
      "subtle": {
        "light": {
          "$type": "color",
          "$value": "{Primitives.color/grey/100}",
          "$description": "Hairline dividers"
        },
        "dark": {
          "$type": "color",
          "$value": "{Primitives.color/grey/800}",
          "$description": "Hairline dividers"
        }
      },
      "strong": {
        "light": {
          "$type": "color",
          "$value": "{Primitives.color/grey/400}",
          "$description": "Form inputs, emphasis"
        },
        "dark": {
          "$type": "color",
          "$value": "{Primitives.color/grey/500}",
          "$description": "Form inputs, emphasis"
        }
      },
      "focus": {
        "light": {
          "$type": "color",
          "$value": "{Primitives.color/blue/500}",
          "$description": "Focus ring"
        },
        "dark": {
          "$type": "color",
          "$value": "{Primitives.color/blue/400}",
          "$description": "Focus ring"
        }
      },
      "brand": {
        "light": {
          "$type": "color",
          "$value": "{Primitives.color/red/500}",
          "$description": "Brand border"
        },
        "dark": {
          "$type": "color",
          "$value": "{Primitives.color/red/400}",
          "$description": "Brand border"
        }
      },
      "breaking": {
        "light": {
          "$type": "color",
          "$value": "{Primitives.color/red/600}",
          "$description": "Breaking news accent"
        },
        "dark": {
          "$type": "color",
          "$value": "{Primitives.color/red/500}",
          "$description": "Breaking news accent"
        }
      }
    },
    "action": {
      "primary": {
        "light": {
          "$type": "color",
          "$value": "{Primitives.color/red/600}",
          "$description": "Primary CTA background"
        },
        "dark": {
          "$type": "color",
          "$value": "{Primitives.color/red/500}",
          "$description": "Primary CTA background"
        }
      },
      "primary-hover": {
        "light": {
          "$type": "color",
          "$value": "{Primitives.color/red/700}",
          "$description": "Primary CTA hover"
        },
        "dark": {
          "$type": "color",
          "$value": "{Primitives.color/red/400}",
          "$description": "Primary CTA hover"
        }
      },
      "primary-active": {
        "light": {
          "$type": "color",
          "$value": "{Primitives.color/red/800}",
          "$description": "Primary CTA active"
        },
        "dark": {
          "$type": "color",
          "$value": "{Primitives.color/red/300}",
          "$description": "Primary CTA active"
        }
      },
      "primary-text": {
        "light": {
          "$type": "color",
          "$value": "{Primitives.color/grey/50}",
          "$description": "Text on primary CTA"
        },
        "dark": {
          "$type": "color",
          "$value": "{Primitives.color/grey/50}",
          "$description": "Text on primary CTA"
        }
      },
      "primary-border": {
        "light": {
          "$type": "color",
          "$value": "{Primitives.color/red/600}",
          "$description": "Primary CTA border"
        },
        "dark": {
          "$type": "color",
          "$value": "{Primitives.color/red/500}",
          "$description": "Primary CTA border"
        }
      },
      "secondary": {
        "light": {
          "$type": "color",
          "$value": "{Primitives.color/grey/100}",
          "$description": "Secondary button bg"
        },
        "dark": {
          "$type": "color",
          "$value": "{Primitives.color/grey/800}",
          "$description": "Secondary button bg"
        }
      },
      "secondary-hover": {
        "light": {
          "$type": "color",
          "$value": "{Primitives.color/grey/200}",
          "$description": "Secondary hover"
        },
        "dark": {
          "$type": "color",
          "$value": "{Primitives.color/grey/700}",
          "$description": "Secondary hover"
        }
      },
      "secondary-active": {
        "light": {
          "$type": "color",
          "$value": "{Primitives.color/grey/300}",
          "$description": "Secondary active"
        },
        "dark": {
          "$type": "color",
          "$value": "{Primitives.color/grey/600}",
          "$description": "Secondary active"
        }
      },
      "secondary-text": {
        "light": {
          "$type": "color",
          "$value": "{Primitives.color/grey/900}",
          "$description": "Secondary button text"
        },
        "dark": {
          "$type": "color",
          "$value": "{Primitives.color/grey/50}",
          "$description": "Secondary button text"
        }
      },
      "secondary-border": {
        "light": {
          "$type": "color",
          "$value": "{Primitives.color/grey/300}",
          "$description": "Secondary border"
        },
        "dark": {
          "$type": "color",
          "$value": "{Primitives.color/grey/600}",
          "$description": "Secondary border"
        }
      },
      "ghost-hover": {
        "light": {
          "$type": "color",
          "$value": "{Primitives.color/grey/100}",
          "$description": "Ghost button hover"
        },
        "dark": {
          "$type": "color",
          "$value": "{Primitives.color/grey/800}",
          "$description": "Ghost button hover"
        }
      },
      "disabled": {
        "light": {
          "$type": "color",
          "$value": "{Primitives.color/grey/100}",
          "$description": "Disabled background"
        },
        "dark": {
          "$type": "color",
          "$value": "{Primitives.color/grey/800}",
          "$description": "Disabled background"
        }
      },
      "disabled-text": {
        "light": {
          "$type": "color",
          "$value": "{Primitives.color/grey/400}",
          "$description": "Disabled text"
        },
        "dark": {
          "$type": "color",
          "$value": "{Primitives.color/grey/600}",
          "$description": "Disabled text"
        }
      }
    },
    "feedback": {
      "success-surface": {
        "light": {
          "$type": "color",
          "$value": "{Primitives.color/green/50}",
          "$description": "Success background"
        },
        "dark": {
          "$type": "color",
          "$value": "{Primitives.color/green/950}",
          "$description": "Success background"
        }
      },
      "success-border": {
        "light": {
          "$type": "color",
          "$value": "{Primitives.color/green/300}",
          "$description": "Success border"
        },
        "dark": {
          "$type": "color",
          "$value": "{Primitives.color/green/700}",
          "$description": "Success border"
        }
      },
      "success-text": {
        "light": {
          "$type": "color",
          "$value": "{Primitives.color/green/700}",
          "$description": "Success text"
        },
        "dark": {
          "$type": "color",
          "$value": "{Primitives.color/green/300}",
          "$description": "Success text"
        }
      },
      "success-icon": {
        "light": {
          "$type": "color",
          "$value": "{Primitives.color/green/500}",
          "$description": "Success icon"
        },
        "dark": {
          "$type": "color",
          "$value": "{Primitives.color/green/400}",
          "$description": "Success icon"
        }
      },
      "warning-surface": {
        "light": {
          "$type": "color",
          "$value": "{Primitives.color/gold/50}",
          "$description": "Warning background"
        },
        "dark": {
          "$type": "color",
          "$value": "{Primitives.color/gold/950}",
          "$description": "Warning background"
        }
      },
      "warning-border": {
        "light": {
          "$type": "color",
          "$value": "{Primitives.color/gold/300}",
          "$description": "Warning border"
        },
        "dark": {
          "$type": "color",
          "$value": "{Primitives.color/gold/700}",
          "$description": "Warning border"
        }
      },
      "warning-text": {
        "light": {
          "$type": "color",
          "$value": "{Primitives.color/gold/800}",
          "$description": "Warning text"
        },
        "dark": {
          "$type": "color",
          "$value": "{Primitives.color/gold/300}",
          "$description": "Warning text"
        }
      },
      "warning-icon": {
        "light": {
          "$type": "color",
          "$value": "{Primitives.color/gold/500}",
          "$description": "Warning icon"
        },
        "dark": {
          "$type": "color",
          "$value": "{Primitives.color/gold/400}",
          "$description": "Warning icon"
        }
      },
      "info-surface": {
        "light": {
          "$type": "color",
          "$value": "{Primitives.color/blue/50}",
          "$description": "Info background"
        },
        "dark": {
          "$type": "color",
          "$value": "{Primitives.color/blue/950}",
          "$description": "Info background"
        }
      },
      "info-border": {
        "light": {
          "$type": "color",
          "$value": "{Primitives.color/blue/300}",
          "$description": "Info border"
        },
        "dark": {
          "$type": "color",
          "$value": "{Primitives.color/blue/700}",
          "$description": "Info border"
        }
      },
      "info-text": {
        "light": {
          "$type": "color",
          "$value": "{Primitives.color/blue/700}",
          "$description": "Info text"
        },
        "dark": {
          "$type": "color",
          "$value": "{Primitives.color/blue/300}",
          "$description": "Info text"
        }
      },
      "info-icon": {
        "light": {
          "$type": "color",
          "$value": "{Primitives.color/blue/500}",
          "$description": "Info icon"
        },
        "dark": {
          "$type": "color",
          "$value": "{Primitives.color/blue/400}",
          "$description": "Info icon"
        }
      },
      "danger-surface": {
        "light": {
          "$type": "color",
          "$value": "{Primitives.color/red/50}",
          "$description": "Danger background"
        },
        "dark": {
          "$type": "color",
          "$value": "{Primitives.color/red/950}",
          "$description": "Danger background"
        }
      },
      "danger-border": {
        "light": {
          "$type": "color",
          "$value": "{Primitives.color/red/300}",
          "$description": "Danger border"
        },
        "dark": {
          "$type": "color",
          "$value": "{Primitives.color/red/700}",
          "$description": "Danger border"
        }
      },
      "danger-text": {
        "light": {
          "$type": "color",
          "$value": "{Primitives.color/red/700}",
          "$description": "Danger text"
        },
        "dark": {
          "$type": "color",
          "$value": "{Primitives.color/red/300}",
          "$description": "Danger text"
        }
      },
      "danger-icon": {
        "light": {
          "$type": "color",
          "$value": "{Primitives.color/red/500}",
          "$description": "Danger icon"
        },
        "dark": {
          "$type": "color",
          "$value": "{Primitives.color/red/400}",
          "$description": "Danger icon"
        }
      }
    }
  }
}